telegram/__init__.py
telegram/dispatcher.py
telegram/handlers.py
telegram/types.py
telegram/updater.py
tigram_nt_bot-0.1.0.dist-info/METADATA
tigram_nt_bot-0.1.0.dist-info/WHEEL
tigram_nt_bot-0.1.0.dist-info/top_level.txt
tigram_nt_bot-0.1.0.dist-info/RECORD
