Metadata-Version: 2.4
Name: tigram_nt_bot
Version: 0.1.0
Summary: A simple pyton telegram libary
Home-page: https://github.com/Amirxon525/py-gram-bot
Author: SN2
Classifier: Programming Language :: Python :: 3
Classifier: License :: OSI Approved :: MIT License
Classifier: Operating System :: OS Independent
Requires-Python: >=3.9
Dynamic: author
Dynamic: classifier
Dynamic: description
Dynamic: description-content-type
Dynamic: home-page
Dynamic: requires-python
Dynamic: summary
